{"enemySlots": [2, 1, 0, 0, 0, 0, 0, 0, 0, 0, 0], "alternatives": {"Darkroot,Iron Keep,Tomb of Giants": [[13, 33, 33], [13, 13, 32], [13, 2, 33], [17, 13, 32]], "Iron Keep": [[2, 2, 2]], "Painted World of Ariamis,Iron Keep,Darkroot": [[20, 33, 33], [17, 20, 32], [20, 2, 33]], "Dark Souls The Board Game,Darkroot,Iron Keep": [[16, 16, 32], [16, 2, 33], [16, 33, 33], [17, 16, 32]], "Darkroot,Iron Keep": [[17, 33, 33], [2, 2, 33]], "Dark Souls The Board Game,Iron Keep,The Sunless City": [[16, 2, 34]], "The Sunless City,Iron Keep,Tomb of Giants": [[13, 2, 34]], "Iron Keep,Darkroot,The Sunless City": [[17, 33, 34], [17, 2, 34]], "Iron Keep,Painted World of Ariamis,The Sunless City": [[20, 2, 34]], "The Sunless City,Painted World of Ariamis,Iron Keep,Tomb of Giants": [[13, 20, 34]], "Dark Souls The Board Game,Painted World of Ariamis,Iron Keep,The Sunless City": [[16, 20, 34]], "Dark Souls The Board Game,Darkroot,Iron Keep,Tomb of Giants": [[16, 13, 32]]}, "original": [2, 2, 2]}